exp_convert/__init__.py
exp_convert/main.py
exp_convert-0.0.1.dist-info/LICENSE.txt
exp_convert-0.0.1.dist-info/METADATA
exp_convert-0.0.1.dist-info/WHEEL
exp_convert-0.0.1.dist-info/top_level.txt
exp_convert-0.0.1.dist-info/RECORD
